MANIFEST.in
README.md
setup.cfg
setup.py
carbon/__init__.py
carbon/urls_favicons.py
carbon/atoms/__init__.py
carbon/atoms/admin/__init__.py
carbon/atoms/admin/content.py
carbon/atoms/admin/media.py
carbon/atoms/admin/rss.py
carbon/atoms/admin/taxonomy.py
carbon/atoms/apps/__init__.py
carbon/atoms/apps/core_apps.py
carbon/atoms/management/__init__.py
carbon/atoms/management/commands/__init__.py
carbon/atoms/management/commands/backup_database.py
carbon/atoms/management/commands/download_file_templates.py
carbon/atoms/management/commands/populate_file_templates.py
carbon/atoms/management/commands/warm_cache_with_sitemap.py
carbon/atoms/managers/__init__.py
carbon/atoms/managers/content.py
carbon/atoms/models/__init__.py
carbon/atoms/models/abstract.py
carbon/atoms/models/access.py
carbon/atoms/models/content.py
carbon/atoms/models/media.py
carbon/atoms/models/rss.py
carbon/atoms/models/user.py
carbon/atoms/sitemap/__init__.py
carbon/atoms/sitemap/abstract.py
carbon/atoms/sitemap/content.py
carbon/atoms/static/admin/css/adjustments.css
carbon/atoms/templates/base.html
carbon/atoms/templates/admin/custom_index.html
carbon/atoms/templates/admin/media/change_list.html
carbon/atoms/templates/admin/media/change_list_image.html
carbon/atoms/templates/admin/media/change_list_image_folders.html
carbon/atoms/templates/admin/media/image_picker.html
carbon/atoms/templates/admin/media/image_picker_folders.html
carbon/atoms/templates/admin/media/move_to_folder.html
carbon/atoms/templates/admin/media/tag_items.html
carbon/atoms/templates/admin/page/import_legacy_urls.html
carbon/atoms/templates/email/emailreceipt_detail.html
carbon/atoms/templates/email/usersubscriptionsettings_detail.html
carbon/atoms/templates/form/form.html
carbon/atoms/templates/form/partials/base_field.html
carbon/atoms/templates/form/partials/base_field_container.html
carbon/atoms/templates/form/partials/check_box.html
carbon/atoms/templates/form/partials/date-time.html
django_carbon.egg-info/PKG-INFO
django_carbon.egg-info/SOURCES.txt
django_carbon.egg-info/dependency_links.txt
django_carbon.egg-info/not-zip-safe
django_carbon.egg-info/requires.txt
django_carbon.egg-info/top_level.txt