Metadata-Version: 1.1
Name: django-carbon
Version: 0.12
Summary: Django Carbon Library
Home-page: https://github.com/ninapavlich/django-carbon/
Author: Nina Pavlich
Author-email: nina@ninalp.com
License: BSD
Platform: UNKNOWN
Classifier: Development Status :: 1 - Planning
Classifier: Environment :: Web Environment
Classifier: Framework :: Django
Classifier: Intended Audience :: Developers
Classifier: License :: OSI Approved
Classifier: Operating System :: OS Independent
Classifier: Programming Language :: Python
